aioshenanigans/__init__.py
aioshenanigans/main.py
aioshenanigans/py.typed
aioshenanigans-0.0.5.dist-info/LICENSE
aioshenanigans-0.0.5.dist-info/METADATA
aioshenanigans-0.0.5.dist-info/WHEEL
aioshenanigans-0.0.5.dist-info/top_level.txt
aioshenanigans-0.0.5.dist-info/RECORD
